diff_tool/__init__.py
diff_tool/cli.py
diff_tool/diff.py
test/__init__.py
test/unit/__init__.py
test/unit/test_diff.py
diff_tool-3.0.0.dist-info/LICENSE
diff_tool-3.0.0.dist-info/METADATA
diff_tool-3.0.0.dist-info/WHEEL
diff_tool-3.0.0.dist-info/entry_points.txt
diff_tool-3.0.0.dist-info/top_level.txt
diff_tool-3.0.0.dist-info/RECORD
