Metadata-Version: 2.1
Name: diff-tool
Version: 3.0.0
Summary: Display a diff between two files in HTML.
Home-page: http://github.com/justintime50/diff-tool
Author: Justintime50
License: MIT
Platform: UNKNOWN
Classifier: Programming Language :: Python :: 3
Classifier: License :: OSI Approved :: MIT License
Classifier: Operating System :: OS Independent
Requires-Python: >=3.7, <4
License-File: LICENSE
Provides-Extra: dev
Requires-Dist: black ; extra == 'dev'
Requires-Dist: coveralls (==3.*) ; extra == 'dev'
Requires-Dist: flake8 ; extra == 'dev'
Requires-Dist: isort ; extra == 'dev'
Requires-Dist: pytest (==6.*) ; extra == 'dev'
Requires-Dist: pytest-cov (==2.*) ; extra == 'dev'
